anavnet/__init__.py
anavnet/anavnet.py
anavnet-0.0.4.data/scripts/anavclient
anavnet-0.0.4.dist-info/METADATA
anavnet-0.0.4.dist-info/RECORD
anavnet-0.0.4.dist-info/WHEEL
anavnet-0.0.4.dist-info/top_level.txt
tests/__init__.py
tests/test_message.py
tests/test_port.py
