Metadata-Version: 2.1
Name: anavnet
Version: 0.0.4
Summary: Client library to the AnavNet website, which provides the current warnings from the Portuguese maritime ports
Home-page: https://github.com/falsovsky/anavnet
Author: Pedro de Oliveira
Author-email: falsovsky@gmail.com
License: BSD-3-Clause
Platform: UNKNOWN
Classifier: Operating System :: OS Independent
Classifier: Programming Language :: Python :: 2
Classifier: Programming Language :: Python :: 2.4
Classifier: Programming Language :: Python :: 2.5
Classifier: Programming Language :: Python :: 2.6
Classifier: Programming Language :: Python :: 2.7
Classifier: Programming Language :: Python :: 3
Classifier: Programming Language :: Python :: 3.3
Classifier: Programming Language :: Python :: 3.4
Classifier: Programming Language :: Python :: 3.5
Classifier: Programming Language :: Python :: 3.6
Classifier: Programming Language :: Python :: 3.7
Requires-Dist: beautifulsoup4
Requires-Dist: requests
